pulumi_kubernetes_the_hard_way/__init__.py
pulumi_kubernetes_the_hard_way/_utilities.py
pulumi_kubernetes_the_hard_way/provider.py
pulumi_kubernetes_the_hard_way/pulumi-plugin.json
pulumi_kubernetes_the_hard_way/py.typed
pulumi_kubernetes_the_hard_way/config/__init__.py
pulumi_kubernetes_the_hard_way/config/_enums.py
pulumi_kubernetes_the_hard_way/config/_inputs.py
pulumi_kubernetes_the_hard_way/config/cni_bridge_plugin_configuration.py
pulumi_kubernetes_the_hard_way/config/cni_loopback_plugin_configuration.py
pulumi_kubernetes_the_hard_way/config/containerd_configuration.py
pulumi_kubernetes_the_hard_way/config/get_cni_bridge_plugin_configuration.py
pulumi_kubernetes_the_hard_way/config/get_cni_loopback_plugin_configuration.py
pulumi_kubernetes_the_hard_way/config/get_containerd_configuration.py
pulumi_kubernetes_the_hard_way/config/get_kube_proxy_configuration.py
pulumi_kubernetes_the_hard_way/config/get_kube_vip_manifest.py
pulumi_kubernetes_the_hard_way/config/get_kubeconfig.py
pulumi_kubernetes_the_hard_way/config/get_kubelet_configuration.py
pulumi_kubernetes_the_hard_way/config/kube_proxy_configuration.py
pulumi_kubernetes_the_hard_way/config/kube_vip_manifest.py
pulumi_kubernetes_the_hard_way/config/kubelet_configuration.py
pulumi_kubernetes_the_hard_way/config/outputs.py
pulumi_kubernetes_the_hard_way/remote/__init__.py
pulumi_kubernetes_the_hard_way/remote/_enums.py
pulumi_kubernetes_the_hard_way/remote/_inputs.py
pulumi_kubernetes_the_hard_way/remote/cni_plugins_install.py
pulumi_kubernetes_the_hard_way/remote/containerd_install.py
pulumi_kubernetes_the_hard_way/remote/containerd_service.py
pulumi_kubernetes_the_hard_way/remote/control_plane_node.py
pulumi_kubernetes_the_hard_way/remote/crictl_install.py
pulumi_kubernetes_the_hard_way/remote/download.py
pulumi_kubernetes_the_hard_way/remote/etcd_cluster.py
pulumi_kubernetes_the_hard_way/remote/etcd_configuration.py
pulumi_kubernetes_the_hard_way/remote/etcd_install.py
pulumi_kubernetes_the_hard_way-0.0.33.dist-info/METADATA
pulumi_kubernetes_the_hard_way-0.0.33.dist-info/WHEEL
pulumi_kubernetes_the_hard_way-0.0.33.dist-info/top_level.txt
pulumi_kubernetes_the_hard_way-0.0.33.dist-info/RECORD
