Metadata-Version: 2.1
Name: pulumi_kubernetes_the_hard_way
Version: 0.0.33
Summary: A Pulumi implementation of Kelsey Hightower's Kubernetes the Hard Way
License: Apache-2.0
Project-URL: Repository, https://github.com/UnstoppableMango/pulumi-kubernetes-the-hard-way
Keywords: pulumi,command,tls,kubernetes,category/utility,kind/component
Requires-Python: >=3.8
Requires-Dist: parver >=0.2.1
Requires-Dist: pulumi <4.0.0,>=3.91.1
Requires-Dist: pulumi-command <2.0.0,>=1.0.0
Requires-Dist: pulumi-kubernetes <5.0.0,>=4.14.0
Requires-Dist: pulumi-random <5.0.0,>=4.16.2
Requires-Dist: pulumi-tls <6.0.0,>=5.0.2
Requires-Dist: semver >=2.8.1
